{
  "main": {
    "id": "22714925c0b90bc0",
    "type": "split",
    "children": [
      {
        "id": "85d602acd1796f19",
        "type": "tabs",
        "children": [
          {
            "id": "fb269d2009dc0453",
            "type": "leaf",
            "state": {
              "type": "markdown",
              "state": {
                "file": "Neuro/notes/Psychophysics.md",
                "mode": "source",
                "source": false
              },
              "icon": "lucide-file",
              "title": "Psychophysics"
            }
          }
        ]
      }
    ],
    "direction": "vertical"
  },
  "left": {
    "id": "6dff4f21fd59efec",
    "type": "split",
    "children": [
      {
        "id": "83b227c11e38092f",
        "type": "tabs",
        "children": [
          {
            "id": "d33edad9dcbd51c7",
            "type": "leaf",
            "state": {
              "type": "file-explorer",
              "state": {
                "sortOrder": "byCreatedTimeReverse",
                "autoReveal": false
              },
              "icon": "lucide-folder-closed",
              "title": "Files"
            }
          },
          {
            "id": "94fddfcc5ba3875c",
            "type": "leaf",
            "state": {
              "type": "search",
              "state": {
                "query": "",
                "matchingCase": false,
                "explainSearch": false,
                "collapseAll": false,
                "extraContext": false,
                "sortOrder": "alphabetical"
              },
              "icon": "lucide-search",
              "title": "Search"
            }
          },
          {
            "id": "4ea53f0f04b949c0",
            "type": "leaf",
            "state": {
              "type": "bookmarks",
              "state": {},
              "icon": "lucide-bookmark",
              "title": "Bookmarks"
            }
          },
          {
            "id": "1a9d31f8146aec41",
            "type": "leaf",
            "state": {
              "type": "recent-files",
              "state": {},
              "icon": "clock",
              "title": "Recent Files"
            }
          }
        ]
      }
    ],
    "direction": "horizontal",
    "width": 200
  },
  "right": {
    "id": "6d17de8421fc9cfd",
    "type": "split",
    "children": [
      {
        "id": "97ee7ed640136ecc",
        "type": "tabs",
        "children": [
          {
            "id": "154b73036fe0c79d",
            "type": "leaf",
            "state": {
              "type": "backlink",
              "state": {
                "file": "00_Dashboard/Weekly Planner.md.md",
                "collapseAll": false,
                "extraContext": false,
                "sortOrder": "alphabetical",
                "showSearch": false,
                "searchQuery": "",
                "backlinkCollapsed": false,
                "unlinkedCollapsed": true
              },
              "icon": "links-coming-in",
              "title": "Backlinks for Weekly Planner.md"
            }
          },
          {
            "id": "d96f7a85a3a006d9",
            "type": "leaf",
            "state": {
              "type": "outgoing-link",
              "state": {
                "linksCollapsed": false,
                "unlinkedCollapsed": true
              },
              "icon": "links-going-out",
              "title": "Outgoing links"
            }
          },
          {
            "id": "7ee58b6b9c83e30d",
            "type": "leaf",
            "state": {
              "type": "tag",
              "state": {
                "sortOrder": "frequency",
                "useHierarchy": true,
                "showSearch": false,
                "searchQuery": ""
              },
              "icon": "lucide-tags",
              "title": "Tags"
            }
          },
          {
            "id": "e0daefc99dd56329",
            "type": "leaf",
            "state": {
              "type": "all-properties",
              "state": {
                "sortOrder": "frequency",
                "showSearch": false,
                "searchQuery": ""
              },
              "icon": "lucide-archive",
              "title": "All properties"
            }
          },
          {
            "id": "07d44353e0eaa50d",
            "type": "leaf",
            "state": {
              "type": "outline",
              "state": {
                "file": "Untitled.md",
                "followCursor": false,
                "showSearch": false,
                "searchQuery": ""
              },
              "icon": "lucide-list",
              "title": "Outline of Untitled"
            }
          },
          {
            "id": "ac8e7fc67b0b9753",
            "type": "leaf",
            "state": {
              "type": "review-queue-list-view",
              "state": {},
              "icon": "SpacedRepIcon",
              "title": "Notes Review Queue"
            }
          },
          {
            "id": "0eda34a365cff185",
            "type": "leaf",
            "state": {
              "type": "git-view",
              "state": {},
              "icon": "lucide-ghost",
              "title": "git-view"
            }
          },
          {
            "id": "efcb3aab72c01941",
            "type": "leaf",
            "state": {
              "type": "review-queue-list-view",
              "state": {},
              "icon": "SpacedRepIcon",
              "title": "Notes Review Queue"
            }
          }
        ],
        "currentTab": 5
      }
    ],
    "direction": "horizontal",
    "width": 200,
    "collapsed": true
  },
  "left-ribbon": {
    "hiddenItems": {
      "switcher:Open quick switcher": false,
      "graph:Open graph view": false,
      "canvas:Create new canvas": false,
      "daily-notes:Open today's daily note": false,
      "templates:Insert template": false,
      "command-palette:Open command palette": false,
      "bases:Create new base": false,
      "markdown-importer:Open format converter": false,
      "darlal-switcher-plus:Open in Headings Mode": false,
      "darlal-switcher-plus:Open Symbols for the active editor": false,
      "obsidian-spaced-repetition:Review flashcards": false,
      "obsidian-git:Open Git source control": false
    }
  },
  "active": "ac8e7fc67b0b9753",
  "lastOpenFiles": [
    "ML/flashcards",
    "ML/notes/fundamental approaches to modeling data.md",
    "ML/notes/Soft Margin SVM.md",
    "ML/notes/Neural Networks.md",
    "Neuro/notes/Psychophysics.md",
    "Neuro/flashcards/Brain Signals.md",
    "Neuro/notes/Brain Signals.md",
    "Neuro/flashcards/Psychophysics.md",
    "Neuro/flashcards/Neurons to Consciousness.md",
    "Neuro/flashcards/Behavioral Readout.md",
    "System Commands/Notes/Linux - Simple Commands.md",
    "System Commands/Notes/Attachments/Pasted image 20260605210535.png",
    "System Commands/Notes/Attachments/Pasted image 20260605205811.png",
    "System Commands/Notes/Attachments/Pasted image 20260605205652.png",
    "System Commands/Notes/Attachments",
    "Math/Discrete Math/books/Discrete and Combinatorial Mathematics by Ralph P Grimaldi.pdf",
    "Math/Discrete Math/books/Discrete Mathematics and its Applications by Kenneth H Rosen.pdf",
    "Math/Discrete Math/books",
    "Computer Science",
    "AI",
    "Computer Science/Python DSA",
    "Computer Science/Computer Networks",
    "Computer Science/DBMS",
    "Computer Science/Operating System",
    "ML/notes/Discriminative Models.md",
    "ML/notes/Generative Models.md",
    "ML/notes/Naive Bayes.md",
    "ML/notes/Perceptron Learning Algorithm.md",
    "ML/notes/Logistic Regression.md",
    "ML/notes/PROBABILISTIC DISCRIMINATIVE MODELS.md",
    "ML/notes/BOUNDARY-BASED DISCRIMINATIVE MODELS.md",
    "ML/notes/Support Vector Machine.md",
    "System Commands/Notes/Command Line Environment.md",
    "System Commands/flashcards/Command line editors.md",
    "System Commands/flashcards/Networking commands and SSH.md",
    "Neuro/flashcards/Neurotransmitters.md",
    "Neuro/flashcards/Stimulus Representation.md",
    "Neuro/notes/Behavioral Readout.md",
    "Neuro/notes/Neurotransmitters.md",
    "System Commands/Attachments/Pasted image 20260601084431.png",
    "System Commands/Attachments/Pasted image 20260601084100.png",
    "System Commands/Attachments/Pasted image 20260601084749.png",
    "System Commands/Attachments/Pasted image 20260601084515.png",
    "System Commands/Attachments/Pasted image 20260601084323.png",
    "Math/Calculus/1. Single Variable/Attachments/Pasted image 20260531125959.png",
    "Math/Calculus/1. Single Variable/Attachments/Pasted image 20260531125930.png"
  ]
}